wsp_cheval/__init__.py
wsp_cheval/_version.py
wsp_cheval/api.py
wsp_cheval/core.py
wsp_cheval/exceptions.py
wsp_cheval/model.py
wsp_cheval/utils.py
wsp_cheval/ldf/__init__.py
wsp_cheval/ldf/api.py
wsp_cheval/ldf/constants.py
wsp_cheval/ldf/missing_data.py
wsp_cheval/parsing/__init__.py
wsp_cheval/parsing/ast_transformer.py
wsp_cheval/parsing/constants.py
wsp_cheval/parsing/exceptions.py
wsp_cheval/parsing/expr_items.py
wsp_cheval/parsing/expressions.py
wsp_cheval-0.3.1.dist-info/licenses/LICENSE
wsp_cheval-0.3.1.dist-info/METADATA
wsp_cheval-0.3.1.dist-info/WHEEL
wsp_cheval-0.3.1.dist-info/top_level.txt
wsp_cheval-0.3.1.dist-info/RECORD
