Metadata-Version: 2.4
Name: wsp-cheval
Version: 0.3.1
Summary: High-performance discrete-choice (logit) travel demand model evaluation
Author-email: Brian Cheung <brian.cheung@wsp.com>, Ashlyn Clarry <ashlyn.clarry@wsp.com>
License-Expression: BSD-3-Clause
Project-URL: Homepage, https://github.com/wsp-sag/cheval
Project-URL: Issues, https://github.com/wsp-sag/cheval/issues
Classifier: Development Status :: 4 - Beta
Classifier: Operating System :: OS Independent
Classifier: Programming Language :: Python :: 3
Requires-Python: <3.11,>=3.9
License-File: LICENSE
Requires-Dist: pandas<1.5,>=0.24
Requires-Dist: numpy<2,>=1.20
Requires-Dist: astor
Requires-Dist: numba>=0.48
Requires-Dist: numexpr
Requires-Dist: attrs>=19.3
Dynamic: license-file
